combine_re_compile/__init__.py
combine_re_compile/tests.py
combine_re_compile-0.0.3.dist-info/LICENSE
combine_re_compile-0.0.3.dist-info/METADATA
combine_re_compile-0.0.3.dist-info/WHEEL
combine_re_compile-0.0.3.dist-info/top_level.txt
combine_re_compile-0.0.3.dist-info/RECORD
