Metadata-Version: 2.1
Name: combine-re-compile
Version: 0.0.3
Summary: combine re compile
Home-page: https://github.com/landybird/combine_re_compile
Author: landybird
Author-email: 1442172978@qq.com
License: UNKNOWN
Platform: UNKNOWN
Classifier: Programming Language :: Python :: 3
Classifier: License :: OSI Approved :: MIT License
Classifier: Operating System :: OS Independent
